{
    "app_id": 40210,
    "name": "ItzaZoo",
    "release_date": "2009-12-09",
    "developer": [
        "Sabi Games"
    ],
    "publisher": [
        "Sabi Games"
    ],
    "platforms": [
        "windows"
    ],
    "required_age": 0,
    "categories": [
        "Single-player"
    ],
    "genres": [
        "Casual"
    ],
    "tags": [
        "Family Friendly"
    ],
    "achievements": 0,
    "positive_ratings": 10,
    "negative_ratings": 0,
    "price": 6.99,
    "description": "Children jump right into a drawing adventure with friendly animals that are ready to play and help them learn to read! Using Living Ink™ – Sabi’s unique drawing recognition system - kid's drawings become one-of-a kind interactive objects that form the centerpiece of the game's action.",
    "header_img": "https://steamcdn-a.akamaihd.net/steam/apps/40210/header.jpg?t=1447352753",
    "minimum_requirements": "OS: Windows XP/Vista/7Processor: 1 Ghz or fasterMemory: 512MB of RAMGraphics: 1024x768 or greater screen resolution, 64MB Directx® 9.0c compliantDirectX&reg;: 9.0c compliantHard Drive: 110MB of free spaceSound: Sound Directx® 9.0c compliant",
    "recommended_requirements": null,
    "reviews": [
        {
            "review_text": "Sequel to the critically acclaimed itzabitza, featuring all the ♥♥♥♥♥ drawing fun of the first game, only now taking place in a zoo.",
            "review_score": "1"
        }
    ]
}