{
    "app_id": 428550,
    "name": "Momodora: Reverie Under The Moonlight",
    "release_date": "2016-03-04",
    "developer": [
        "Bombservice"
    ],
    "publisher": [
        "AGM PLAYISM"
    ],
    "platforms": [
        "windows",
        "mac",
        "linux"
    ],
    "required_age": 0,
    "categories": [
        "Single-player",
        "Steam Achievements",
        "Full controller support",
        "Steam Trading Cards",
        "Steam Cloud"
    ],
    "genres": [
        "Action",
        "Adventure",
        "Indie"
    ],
    "tags": [
        "Pixel Graphics",
        "Metroidvania",
        "Female Protagonist"
    ],
    "achievements": 9,
    "positive_ratings": 5904,
    "negative_ratings": 363,
    "price": 6.99,
    "description": "Momodora: Reverie Under The Moonlight is the fourth installment in the beloved Momodora series of 2D platformers. Unleash ravaging combos against a variety of formidable monsters and deftly dodge your way through a cursed land to seek audience with the Queen and dispel the evil that threatens all life.",
    "header_img": "https://steamcdn-a.akamaihd.net/steam/apps/428550/header.jpg?t=1554710110",
    "minimum_requirements": "OS: Windows 7 Processor: 1.2 Ghz or superior Memory: 2 GB RAM Graphics: 256 MB Storage: 200 MB available space",
    "recommended_requirements": "OS: Windows 7 Processor: 2 Ghz Memory: 2 GB RAM Graphics: 1 GB (with Pixel Shader support) Storage: 200 MB available space",
    "reviews": []
}