{
    "app_id": 573740,
    "name": "Northern Tale 4",
    "release_date": "2017-11-16",
    "developer": [
        "Realore"
    ],
    "publisher": [
        "Qumaron"
    ],
    "platforms": [
        "windows"
    ],
    "required_age": 0,
    "categories": [
        "Single-player"
    ],
    "genres": [
        "Adventure",
        "Casual",
        "Simulation",
        "Strategy"
    ],
    "tags": [
        "Casual",
        "Strategy",
        "Adventure"
    ],
    "achievements": 0,
    "positive_ratings": 5,
    "negative_ratings": 1,
    "price": 3.99,
    "description": "In Northern Tale 4, Ragnar's kingdom is in danger once again. After defeating the evil witch Gesta and the Dragon of Ether, the Viking lands are on the verge of a new invasion. Collect, repair and build to defend against a vast army of Giants, Witches and Black Knights.",
    "header_img": "https://steamcdn-a.akamaihd.net/steam/apps/573740/header.jpg?t=1542718711",
    "minimum_requirements": "OS: Windows XP/Vista/Windows 7/Windows 8/Windows 10 Processor: Pentium III 800MHz Memory: 256 MB RAM Graphics: Graphics card with 32MB Video RAM Storage: 750 MB available space",
    "recommended_requirements": null,
    "reviews": []
}