{
    "app_id": 633370,
    "name": "Who's your Santa !?",
    "release_date": "2017-12-18",
    "developer": [
        "5Wolf"
    ],
    "publisher": [
        "5Wolf"
    ],
    "platforms": [
        "windows"
    ],
    "required_age": 18,
    "categories": [
        "Single-player",
        "Steam Achievements",
        "Steam Trading Cards"
    ],
    "genres": [
        "Adventure",
        "Indie",
        "Racing"
    ],
    "tags": [
        "Sexual Content",
        "Indie",
        "Nudity"
    ],
    "achievements": 222,
    "positive_ratings": 221,
    "negative_ratings": 34,
    "price": 3.19,
    "description": "The game is the puzzle that will wreck a couple of your brain cells! The game that will test your maddest fantasies. If you’ll finish it on the first try, you should then ask yourself: “Am I alright?” The game after finishing which you’ll need 5 years of enhanced therapy. And us too, btw.",
    "header_img": "https://steamcdn-a.akamaihd.net/steam/apps/633370/header.jpg?t=1548515005",
    "minimum_requirements": "OS: Windows 7 Processor: Core 2 Duo Memory: 1024 MB RAM Graphics: Integrated Graphics Storage: 1000 MB available space Sound Card: Integrated Audio",
    "recommended_requirements": null,
    "reviews": []
}