{
    "app_id": 640050,
    "name": "Soldiers of the Universe",
    "release_date": "2017-11-30",
    "developer": [
        "Rocwise Entertainment"
    ],
    "publisher": [
        "Rocwise Entertainment"
    ],
    "platforms": [
        "windows"
    ],
    "required_age": 0,
    "categories": [
        "Single-player",
        "Co-op",
        "Online Co-op",
        "Partial Controller Support"
    ],
    "genres": [
        "Violent",
        "Gore",
        "Action",
        "Adventure",
        "Indie"
    ],
    "tags": [
        "Action",
        "Adventure",
        "Indie"
    ],
    "achievements": 0,
    "positive_ratings": 206,
    "negative_ratings": 191,
    "price": 3.99,
    "description": "Soldiers of the Universe is a Story-Driven First Person Shooter game that tells the story of a group of soldiers fighting against terrorist organizations in the Middle-East.",
    "header_img": "https://steamcdn-a.akamaihd.net/steam/apps/640050/header.jpg?t=1512140241",
    "minimum_requirements": "Requires a 64-bit processor and operating system OS: Windows 7 64-Bit or later Processor: Intel Core i3-3225 @ 3.30GHz Memory: 4 GB RAM Graphics: nVidia GeForce GTX 500 Series 1GB / AMD Radeon HD 6000 Series 1GB DirectX: Version 11 Storage: 15 GB available space Sound Card: N/A",
    "recommended_requirements": "Requires a 64-bit processor and operating system",
    "reviews": []
}