{
    "app_id": 676070,
    "name": "an Orc's Tale: Kriegsruf",
    "release_date": "2017-08-15",
    "developer": [
        "Deydrihm"
    ],
    "publisher": [
        "Deydrihm"
    ],
    "platforms": [
        "windows"
    ],
    "required_age": 0,
    "categories": [
        "Single-player",
        "Partial Controller Support",
        "Commentary available"
    ],
    "genres": [
        "Violent",
        "Adventure",
        "Free to Play",
        "Indie",
        "RPG",
        "Early Access"
    ],
    "tags": [
        "Early Access",
        "Free to Play",
        "Adventure"
    ],
    "achievements": 0,
    "positive_ratings": 14,
    "negative_ratings": 6,
    "price": 0.0,
    "description": "Die Geschichte eines jungen Orks in den Wirren eines Krieges, der zu gross für einen einzelnen Krieger ist. Storylastiges RPG im Stil der alten Klassiker, mit modernen Mitteln dargestellt, ohne den alten Charme zu verlieren mit etlichen handgestalteten Grafiken und Effekten.",
    "header_img": "https://steamcdn-a.akamaihd.net/steam/apps/676070/header.jpg?t=1510173905",
    "minimum_requirements": "OS: Windows 7 32bit Processor: Intel(R) Core(TM) i74770 CPU 3.40GHz Memory: 4 GB RAM Graphics: Aktuelle Grafikkarte Storage: 2 GB available space Sound Card: Aktuelle Soundkarte",
    "recommended_requirements": "OS: Windows 7 64bit Processor: Intel(R) Core(TM) i74770 CPU 3.40GHz oder besser Memory: 16 GB RAM Graphics: Aktuelle Grafikkarte Storage: 2 GB available space Sound Card: Aktuelle Soundkarte",
    "reviews": []
}