{
    "app_id": 698160,
    "name": "DinosaurIsland",
    "release_date": "2017-09-03",
    "developer": [
        "LiangDeZhao"
    ],
    "publisher": [
        "LiangDeZhao"
    ],
    "platforms": [
        "windows"
    ],
    "required_age": 0,
    "categories": [
        "Single-player"
    ],
    "genres": [
        "Violent",
        "Action",
        "Adventure",
        "Indie"
    ],
    "tags": [
        "Action",
        "Indie",
        "Adventure"
    ],
    "achievements": 0,
    "positive_ratings": 2,
    "negative_ratings": 7,
    "price": 2.79,
    "description": "A survival and killing adventure game, thrilling death exploration, cooking all kinds of food, making weapons, looking for resources, and enjoying breathtaking Adventures. Live and explore in a dark environment, and always be on guard.",
    "header_img": "https://steamcdn-a.akamaihd.net/steam/apps/698160/header.jpg?t=1504504898",
    "minimum_requirements": "OS: Windows 7 Processor: Intel i5  4590 Memory: 8 GB RAM Graphics: NVIDIA GTX 970 / AMD 290 DirectX: Version 11 Storage: 15 GB available space",
    "recommended_requirements": "OS: Windows 7 Processor: Intel i7  4790 Memory: 16 GB RAM Graphics: NVIDIA GTX 970 / AMD 290 DirectX: Version 11 Storage: 15 GB available space",
    "reviews": []
}