{
    "app_id": 743110,
    "name": "Shit Storm",
    "release_date": "2017-12-27",
    "developer": [
        "Floor Chicken"
    ],
    "publisher": [
        "Floor Chicken"
    ],
    "platforms": [
        "windows"
    ],
    "required_age": 0,
    "categories": [
        "Single-player",
        "Steam Achievements"
    ],
    "genres": [
        "Nudity",
        "Violent",
        "Action",
        "Adventure",
        "Casual",
        "Indie",
        "Simulation"
    ],
    "tags": [
        "Action",
        "Indie",
        "Casual"
    ],
    "achievements": 8,
    "positive_ratings": 15,
    "negative_ratings": 2,
    "price": 1.69,
    "description": "Your butt is lost in space. Dodge enemies and consume foods in order to survive but watch out because in space no one can hear you shit.",
    "header_img": "https://steamcdn-a.akamaihd.net/steam/apps/743110/header.jpg?t=1514367902",
    "minimum_requirements": "OS: Windows 7 Processor: Intel i5 2410m @ 2.3GHz Memory: 4 GB RAM Graphics: Intel HD Graphics 3000 DirectX: Version 10 Storage: 100 MB available space Additional Notes: Let's be serious, chances are a potato can run this but this is as bad as my worst computer goes.",
    "recommended_requirements": null,
    "reviews": []
}