{
    "app_id": 761620,
    "name": "Beholder 2",
    "release_date": "2018-12-04",
    "developer": [
        "Warm Lamp Games"
    ],
    "publisher": [
        "Alawar Premium"
    ],
    "platforms": [
        "windows",
        "mac",
        "linux"
    ],
    "required_age": 0,
    "categories": [
        "Single-player",
        "Steam Achievements",
        "Steam Trading Cards",
        "Steam Workshop",
        "Partial Controller Support",
        "Steam Cloud"
    ],
    "genres": [
        "Adventure",
        "Indie",
        "Simulation",
        "Strategy"
    ],
    "tags": [
        "Strategy",
        "Adventure",
        "Dystopian "
    ],
    "achievements": 52,
    "positive_ratings": 987,
    "negative_ratings": 190,
    "price": 9.99,
    "description": "You are a newly employed department officer within the Ministry of a totalitarian State. While you are poised to have an illustrious career and possibly become Prime Minister someday, the way up won't be easy. So, how high up the career ladder will you climb? The choice is still yours to make!",
    "header_img": "https://steamcdn-a.akamaihd.net/steam/apps/761620/header.jpg?t=1549527560",
    "minimum_requirements": "OS: Windows 7/8/10 (64-bit OS required) Processor: Intel Core 2 Quad Q6600 @ 2.4 GHz, AMD FX 8120 @ 3.1 GHz Memory: 4 GB RAM Graphics: NVIDIA GT 630 / 650m, AMD Radeon HD6570 or equivalent DirectX: Version 9.0c Storage: 4 GB available space Sound Card: 100% DirectX 9.0c compatible Additional Notes: ADDITIONAL SYSTEM REQUIREMENTS: Loyalty to the System! Devotion to the State! Trust in the infallibility of the Wise Leader! Basic Bureaucracy skills.",
    "recommended_requirements": "OS: Windows 8/10 (64-bit OS required) Processor: Intel i7 920 @ 2.7 GHz, AMD Phenom II 945 @ 3.0 GHz Memory: 8 GB RAM Graphics: NVIDIA GTX 660, Radeon R9-270 DirectX: Version 11 Storage: 4 GB available space Sound Card: 100% DirectX 9.0c compatible",
    "reviews": []
}