{
    "app_id": 780850,
    "name": "Recreational Dreaming",
    "release_date": "2018-01-31",
    "developer": [
        "Donald Dunbar",
        "Ryan Donaldson"
    ],
    "publisher": [
        "Eyedrop"
    ],
    "platforms": [
        "windows"
    ],
    "required_age": 0,
    "categories": [
        "Single-player"
    ],
    "genres": [
        "Casual",
        "Indie"
    ],
    "tags": [
        "Indie",
        "Casual",
        "VR"
    ],
    "achievements": 0,
    "positive_ratings": 6,
    "negative_ratings": 0,
    "price": 4.79,
    "description": "Recreational Dreaming is a casual stroll through a softer, shinier mind. Explore, shoot, and chill.",
    "header_img": "https://steamcdn-a.akamaihd.net/steam/apps/780850/header.jpg?t=1517888902",
    "minimum_requirements": "OS: Windows 7 Processor: Intel(R) Core(TM) i5-6402P CPU @ 2.80 GHz, 2808 Mhz, 4 Cores Memory: 4 GB RAM Graphics: Radeon (TM) RX 480 Graphics Storage: 1 GB available space Additional Notes: Should run fine on any &quot;VR Ready&quot; machine",
    "recommended_requirements": null,
    "reviews": []
}