{
    "app_id": 789620,
    "name": "Crypt- The Black Tower",
    "release_date": "2018-03-09",
    "developer": [
        "Endless Void Studios"
    ],
    "publisher": [
        "Endless Void Studios"
    ],
    "platforms": [
        "windows"
    ],
    "required_age": 0,
    "categories": [
        "Single-player"
    ],
    "genres": [
        "Action",
        "Adventure",
        "Casual",
        "Free to Play",
        "Indie",
        "RPG"
    ],
    "tags": [
        "Action",
        "Adventure",
        "Free to Play"
    ],
    "achievements": 0,
    "positive_ratings": 99,
    "negative_ratings": 29,
    "price": 0.0,
    "description": "Crypt is a 3rd person click to move adventure based RPG that takes you deep into the ancient and forgotten places of a long dead world. rise as an un-dead skeleton and begin your war path of magical carnage.",
    "header_img": "https://steamcdn-a.akamaihd.net/steam/apps/789620/header.jpg?t=1532066072",
    "minimum_requirements": "OS: •Windows XP, Vista 7 or 10 Processor: •Pentium CPU Running At 2.8GHz or Higher. Memory: 4 GB RAM Graphics: •Dedicated, Accelerated 3D-Graphics Card and Drivers: or better Storage: 1400 MB available space",
    "recommended_requirements": "OS: •Windows XP, Vista 7 or 10 Processor: •Pentium CPU Running At 2.8GHz or Higher. Memory: 4 GB RAM Graphics: •Dedicated, Accelerated 3D-Graphics Card and Drivers: or better Storage: 1600 MB available space",
    "reviews": []
}