{
    "app_id": 887400,
    "name": "The Great Geometric Multiverse Tour",
    "release_date": "2018-08-27",
    "developer": [
        "Pie On A Plate Productions"
    ],
    "publisher": [
        "Pie On A Plate Productions"
    ],
    "platforms": [
        "windows",
        "mac",
        "linux"
    ],
    "required_age": 0,
    "categories": [
        "Single-player",
        "Steam Achievements",
        "Full controller support"
    ],
    "genres": [
        "Action",
        "Adventure",
        "Indie"
    ],
    "tags": [
        "Action",
        "Indie",
        "Adventure"
    ],
    "achievements": 17,
    "positive_ratings": 9,
    "negative_ratings": 0,
    "price": 10.29,
    "description": "LIBERATE THE GEOMETRIC PEOPLE AND SAVE THE MULTIVERSE! Fight through the randomly chosen universes of the Geometric Multiverse, arming yourself to the teeth with insane weaponry and mutating your mind, body, and soul with the unrelenting power of genetically altering pills.",
    "header_img": "https://steamcdn-a.akamaihd.net/steam/apps/887400/header.jpg?t=1545370873",
    "minimum_requirements": "OS: Windows 7/8.1/10 Processor: 2.5GHz Memory: 4 GB RAM Graphics: Intel HD Graphics 128 MB Storage: 2 GB available space Additional Notes: Only Xbox360 and XboxOne controllers currently supported (But a mouse and keyboard are recommended anyways)",
    "recommended_requirements": "OS: Windows 7/8.1/10 Processor: 3.0GHz Memory: 4 GB RAM Graphics: 1 GB VRAM Storage: 2 GB available space Additional Notes: Only Xbox360 and XboxOne controllers currently supported (But a mouse and keyboard are recommended anyways)",
    "reviews": []
}