{
    "app_id": 898340,
    "name": "Puzzles and Board Games Mega Collection",
    "release_date": "2018-07-25",
    "developer": [
        "Gunnar Games"
    ],
    "publisher": [
        "Gunnar Games"
    ],
    "platforms": [
        "windows"
    ],
    "required_age": 0,
    "categories": [
        "Single-player"
    ],
    "genres": [
        "Casual"
    ],
    "tags": [
        "Casual",
        "Board Game"
    ],
    "achievements": 0,
    "positive_ratings": 1,
    "negative_ratings": 3,
    "price": 5.19,
    "description": "10 of the most popular Puzzles and Board Games all in one collection.",
    "header_img": "https://steamcdn-a.akamaihd.net/steam/apps/898340/header.jpg?t=1532572928",
    "minimum_requirements": "OS: Windows Vista Processor: 3 GHz Memory: 2 MB RAM Graphics: DirectX compatible video card DirectX: Version 9.0 Storage: 200 MB available space Sound Card: DirectX compatible sound card",
    "recommended_requirements": null,
    "reviews": []
}