{
    "app_id": 912390,
    "name": "Dismantle: Construct Carnage",
    "release_date": "2019-02-13",
    "developer": [
        "Great Helm"
    ],
    "publisher": [
        "Great Helm"
    ],
    "platforms": [
        "windows"
    ],
    "required_age": 0,
    "categories": [
        "Single-player",
        "Local Multi-Player",
        "Local Co-op",
        "Shared/Split Screen",
        "Steam Achievements",
        "Full controller support"
    ],
    "genres": [
        "Action",
        "Indie"
    ],
    "tags": [
        "Action",
        "Indie",
        "Fighting"
    ],
    "achievements": 15,
    "positive_ratings": 6,
    "negative_ratings": 1,
    "price": 9.29,
    "description": "‘Dismantle: Construct Carnage’, is a local-multiplayer arena brawler, where you can literally tear your opponents limb from limb. Feel the effects of damage as you hop, crawl and roll your way to victory, making sure your own body parts aren’t used as weapons against you.",
    "header_img": "https://steamcdn-a.akamaihd.net/steam/apps/912390/header.jpg?t=1550080831",
    "minimum_requirements": "OS: Windows 7 64-bit or later Processor: i5-3570 @ 3.40 GHz (or equivalent) Memory: 4 GB RAM Graphics: GeForce GTX 460M (or equivalent) Storage: 1500 MB available space Additional Notes: 30fps @ 720p with Low Settings",
    "recommended_requirements": "OS: Windows 10 64-bit or later Processor: i7-2700k @ 3.50 GHz (or equivalent) Memory: 4 GB RAM Graphics: GeForce GTX 560 (or equivalent) Storage: 1500 MB available space Additional Notes: 60fps @ 1080p with High Settings",
    "reviews": []
}