{
    "app_id": 921740,
    "name": "Shahrzad - The Storyteller",
    "release_date": "2018-08-17",
    "developer": [
        "Electro gryphon gamelab"
    ],
    "publisher": [
        "Libredia Entertainment"
    ],
    "platforms": [
        "windows"
    ],
    "required_age": 0,
    "categories": [
        "Single-player"
    ],
    "genres": [
        "Casual"
    ],
    "tags": [
        "Casual",
        "Hidden Object",
        "Adventure"
    ],
    "achievements": 0,
    "positive_ratings": 1,
    "negative_ratings": 0,
    "price": 7.19,
    "description": "Shahrzad - The Storyteller is a stunningly beautiful hidden object game with over 60 puzzles and minigames. Let the world of 1001 Persian nights mystify you!",
    "header_img": "https://steamcdn-a.akamaihd.net/steam/apps/921740/header.jpg?t=1538739847",
    "minimum_requirements": "OS: Windiows 7 or higher Processor: 2 GHz or higher Memory: 1 GB RAM Graphics: VGA with 512MB Memory DirectX: Version 9.0c Storage: 450 MB available space Sound Card: recommended",
    "recommended_requirements": null,
    "reviews": []
}